pythonplot/__about__.py
pythonplot/__init__.py
pythonplot/_temp.py
pythonplot/Dependencies/__init__.py
pythonplot/_scripts/__init__.py
pythonplot/_scripts/pplot.py
pythonplot-0.0.1.dist-info/METADATA
pythonplot-0.0.1.dist-info/WHEEL
pythonplot-0.0.1.dist-info/RECORD
